{"ongoing_trials": {"tuner0": "00"}, "hyperparameters": {"space": [{"class_name": "Choice", "config": {"name": "units", "default": 32, "conditions": [], "values": [32, 64, 128], "ordered": true}}, {"class_name": "Choice", "config": {"name": "learning_rate", "default": 0.01, "conditions": [], "values": [0.01, 0.001, 0.0001], "ordered": true}}], "values": {"units": 32, "learning_rate": 0.01}}, "start_order": ["00"], "end_order": [], "run_times": {}, "retry_queue": [], "seed": 1425, "seed_state": 1427, "tried_so_far": ["7c1a8637e90c340863407ea163306ab5"], "id_to_hash": {"00": "7c1a8637e90c340863407ea163306ab5"}, "display": {"search_start": null, "trial_start": {}, "trial_number": {}}}